nonebot_plugin_csgomarket/__init__.py
nonebot_plugin_csgomarket/database.py
nonebot_plugin_csgomarket/items.py
nonebot_plugin_csgomarket/templates/css/font.css
nonebot_plugin_csgomarket/templates/css/item.css
nonebot_plugin_csgomarket/templates/css/markets.css
nonebot_plugin_csgomarket/templates/css/pop_up_modle.css
nonebot_plugin_csgomarket/templates/css/rank.css
nonebot_plugin_csgomarket/templates/css/search.css
nonebot_plugin_csgomarket/templates/css/style.css
nonebot_plugin_csgomarket/templates/item.html
nonebot_plugin_csgomarket/templates/item.html.jinja2
nonebot_plugin_csgomarket/templates/js/customize.js
nonebot_plugin_csgomarket/templates/js/echarts.min.js
nonebot_plugin_csgomarket/templates/js/gsap.min.js
nonebot_plugin_csgomarket/templates/js/item.js
nonebot_plugin_csgomarket/templates/js/item_1.js
nonebot_plugin_csgomarket/templates/js/item_2.js
nonebot_plugin_csgomarket/templates/js/klinecharts.min.js
nonebot_plugin_csgomarket/templates/js/lottie.min.js
nonebot_plugin_csgomarket/templates/js/markets.js
nonebot_plugin_csgomarket/templates/js/markets_1.js
nonebot_plugin_csgomarket/templates/js/markets_2.js
nonebot_plugin_csgomarket/templates/js/markets_3.js
nonebot_plugin_csgomarket/templates/js/markets_4.js
nonebot_plugin_csgomarket/templates/js/md5.min.js
nonebot_plugin_csgomarket/templates/js/name.json.js
nonebot_plugin_csgomarket/templates/js/presets.js
nonebot_plugin_csgomarket/templates/js/rank.js
nonebot_plugin_csgomarket/templates/js/script.js
nonebot_plugin_csgomarket/templates/js/search.js
nonebot_plugin_csgomarket/templates/markets.html
nonebot_plugin_csgomarket/templates/markets.html.jinja2
nonebot_plugin_csgomarket/templates/rank.html
nonebot_plugin_csgomarket/templates/rank.html.jinja2
nonebot_plugin_csgomarket/templates/search.html
nonebot_plugin_csgomarket/templates/search.html.jinja2
nonebot_plugin_csgomarket-0.2.1.dist-info/LICENSE
nonebot_plugin_csgomarket-0.2.1.dist-info/METADATA
nonebot_plugin_csgomarket-0.2.1.dist-info/WHEEL
nonebot_plugin_csgomarket-0.2.1.dist-info/RECORD
