Metadata-Version: 2.1
Name: nonebot-plugin-csgomarket
Version: 0.2.1
Summary: 可以查询 Counter Strike 2 市场信息，包括大盘数据、饰品信息与各类排行榜。
Home-page: https://github.com/Florenz0707/nonebot-plugin-csgomarket.git
Author: florenz
Requires-Python: >=3.9,<4.0
Classifier: Programming Language :: Python :: 3
Classifier: Programming Language :: Python :: 3.9
Classifier: Programming Language :: Python :: 3.10
Classifier: Programming Language :: Python :: 3.11
Classifier: Programming Language :: Python :: 3.12
Classifier: Programming Language :: Python :: 3.13
Requires-Dist: jinja2 (>=3.1.4)
Requires-Dist: nonebot-plugin-alconna (>=0.53.1)
Requires-Dist: nonebot-plugin-htmlrender (>=0.3.5)
Requires-Dist: nonebot-plugin-waiter (>=0.8.0)
Requires-Dist: nonebot2 (>=2.4.0)
Project-URL: Repository, https://github.com/Florenz0707/nonebot-plugin-csgomarket.git
